MANIFEST.in
README.rst
setup.cfg
setup.py
data/__init__.py
data/exceptions.py
data/services.py
data/time.py
data/parsers/__init__.py
data/parsers/movies.py
data/parsers/theaters.py
flix.egg-info/PKG-INFO
flix.egg-info/SOURCES.txt
flix.egg-info/dependency_links.txt
flix.egg-info/entry_points.txt
flix.egg-info/requires.txt
flix.egg-info/top_level.txt
scripts/__init__.py
scripts/flix.py
tables/__init__.py
tables/builders.py
tables/utilities.py
tables/rows/__init__.py
tables/rows/builders.py