Metadata-Version: 1.1
Name: flix
Version: 0.0.1
Summary: Movie CLI
Home-page: https://github.com/jaebradley/flix
Author: Jae Bradley
Author-email: jae.b.bradley@gmail.com
License: UNKNOWN
Download-URL: https://github.com/jaebradley/flix/tarball/0.1
Keywords: flixster,movies,cli
Platform: UNKNOWN
